graphene_django_filter/__init__.py
graphene_django_filter/conf.py
graphene_django_filter/connection_field.py
graphene_django_filter/filter_arguments_factory.py
graphene_django_filter/filters.py
graphene_django_filter/filterset.py
graphene_django_filter/filterset_factories.py
graphene_django_filter/input_data_factories.py
graphene_django_filter/input_types.py
graphene_django_filter-0.6.5.dist-info/LICENSE
graphene_django_filter-0.6.5.dist-info/METADATA
graphene_django_filter-0.6.5.dist-info/WHEEL
graphene_django_filter-0.6.5.dist-info/RECORD
