Metadata-Version: 2.1
Name: graphene-django-filter
Version: 0.6.5
Summary: Advanced filters for Graphene
Home-page: https://github.com/devind-team/graphene-django-filter
License: MIT
Keywords: django,graphene,filter
Author: devind-team
Author-email: team@devind.ru
Requires-Python: >=3.8,<4.0
Classifier: Framework :: Django
Classifier: License :: OSI Approved :: MIT License
Classifier: Operating System :: OS Independent
Classifier: Programming Language :: Python :: 3
Classifier: Programming Language :: Python :: 3.8
Classifier: Programming Language :: Python :: 3.9
Classifier: Programming Language :: Python :: 3.10
Classifier: Programming Language :: Python :: 3.11
Requires-Dist: Django (>=3,<4.3)
Requires-Dist: anytree (>=2.8.0,<3.0.0)
Requires-Dist: django-filter (>=21.1,<22.0)
Requires-Dist: graphene (>=2.1.9,<4)
Requires-Dist: graphene-django (>=3.0.0,<4.0.0)
Requires-Dist: psycopg2-binary (>=2.9.3,<3.0.0)
Requires-Dist: stringcase (>=1.2.0,<2.0.0)
Requires-Dist: wrapt (>=1.14.0,<2.0.0)
Project-URL: Repository, https://github.com/devind-team/graphene-django-filter
